camerahub_tagger/__init__.py
camerahub_tagger/api.py
camerahub_tagger/config.py
camerahub_tagger/funcs.py
camerahub_tagger/main.py
camerahub_tagger-0.6.0.dist-info/METADATA
camerahub_tagger-0.6.0.dist-info/WHEEL
camerahub_tagger-0.6.0.dist-info/entry_points.txt
camerahub_tagger-0.6.0.dist-info/RECORD
