Metadata-Version: 2.1
Name: camerahub-tagger
Version: 0.6.0
Summary: EXIF tagger for CameraHub
Home-page: https://camerahub.info/
Keywords: EXIF,photography,CameraHub,metadata
Author: Jonathan Gazeley
Author-email: me@jonathangazeley.com
Requires-Python: >=3.9,<4.0
Classifier: Programming Language :: Python :: 3
Classifier: Programming Language :: Python :: 3.9
Classifier: Programming Language :: Python :: 3.10
Classifier: Programming Language :: Python :: 3.11
Requires-Dist: deepdiff (>=6.3.0,<7.0.0)
Requires-Dist: pyexiv2 (>=2.8.1,<3.0.0)
Requires-Dist: requests (>=2.26.0,<3.0.0)
Requires-Dist: termcolor (>=2.3.0,<3.0.0)
Requires-Dist: uuid (>=1.30,<2.0)
Project-URL: Repository, https://github.com/camerahub/tagger
